{
    "compact": true,
    "controlFlowFlattening": true,
    "controlFlowFlatteningThreshold": 0.4,
    "deadCodeInjection": true,
    "deadCodeInjectionThreshold": 0.3,
    "debugProtection": false,
    "debugProtectionInterval": 3000,
    "disableConsoleOutput": false,
    "identifierNamesGenerator": "hexadecimal",
    "log": false,
    "numbersToExpressions": true,
    "renameGlobals": true,
    "selfDefending": false,
    "simplify": true,
    "splitStrings": true,
    "splitStringsChunkLength": 10,
    "stringArray": true,
    "stringArrayCallsTransform": true,
    "stringArrayEncoding": [
        "rc4",
        "base64"
    ],
    "stringArrayIndexShift": true,
    "stringArrayRotate": true,
    "stringArrayShuffle": true,
    "stringArrayWrappersCount": 4,
    "stringArrayWrappersChainedCalls": true,
    "stringArrayWrappersParametersMaxCount": 4,
    "stringArrayWrappersType": "function",
    "stringArrayThreshold": 0.4,
    "transformObjectKeys": true,
    "unicodeEscapeSequence": false
}